bhpq/__init__.py
bhpq/_version.py
bhpq/bhpq.py
bhpq-2.0.1.dist-info/LICENSE
bhpq-2.0.1.dist-info/METADATA
bhpq-2.0.1.dist-info/WHEEL
bhpq-2.0.1.dist-info/top_level.txt
bhpq-2.0.1.dist-info/RECORD
