Metadata-Version: 2.1
Name: bhpq
Version: 2.0.1
Summary: Binary Heap Priority Queue
Home-page: https://github.com/aayushuppal/bhpq
Author: Aayush Uppal
Author-email: aayuppal@gmail.com
License: MIT
Platform: UNKNOWN
Classifier: License :: OSI Approved :: MIT License
Classifier: Programming Language :: Python
Classifier: Programming Language :: Python :: 3
